{"stats":{"minecraft:picked_up":{"minecraft:lime_concrete":1,"minecraft:orange_concrete":9},"minecraft:custom":{"minecraft:jump":574,"minecraft:time_since_rest":7369,"minecraft:damage_taken":780,"minecraft:leave_game":3,"minecraft:crouch_one_cm":541,"minecraft:time_since_death":6293,"minecraft:play_time":26178,"minecraft:sprint_one_cm":80969,"minecraft:walk_one_cm":24529,"minecraft:walk_on_water_one_cm":532,"minecraft:deaths":2,"minecraft:sneak_time":300,"minecraft:total_world_time":26178,"minecraft:drop":48,"minecraft:fall_one_cm":14047,"minecraft:fly_one_cm":278635},"minecraft:dropped":{"minecraft:lime_concrete":27,"minecraft:magenta_concrete":27,"minecraft:red_concrete":29,"minecraft:orange_concrete":27,"minecraft:light_blue_concrete":9}},"DataVersion":2865}